django_issueinspector-0.2.1.dist-info/DESCRIPTION.rst
django_issueinspector-0.2.1.dist-info/METADATA
django_issueinspector-0.2.1.dist-info/RECORD
django_issueinspector-0.2.1.dist-info/WHEEL
django_issueinspector-0.2.1.dist-info/metadata.json
django_issueinspector-0.2.1.dist-info/top_level.txt
issueinspector/__init__.py
issueinspector/models.py
issueinspector/utils.py
issueinspector/views.py
issueinspector/templates/issueinspector/index.html
issueinspector/templates/issueinspector/sub_issues.html
