Metadata-Version: 2.0
Name: django-issueinspector
Version: 0.2.1
Summary: Issue inspector for your GitHub repositories
Home-page: https://github.com/idlesign/django-issueinspector
Author: Igor `idle sign` Starikov
Author-email: idlesign@yandex.ru
License: BSD 3-Clause License
Platform: UNKNOWN
Classifier: Development Status :: 4 - Beta
Classifier: Operating System :: OS Independent
Classifier: Programming Language :: Python
Classifier: Programming Language :: Python :: 3
Classifier: Programming Language :: Python :: 3.2
Classifier: Programming Language :: Python :: 3.3
Classifier: Programming Language :: Python :: 3.4
Classifier: Programming Language :: Python :: 3.5
Classifier: License :: OSI Approved :: BSD License
Requires-Dist: django-xross
Requires-Dist: requests
